MANIFEST.in
README.md
module.md
setup.cfg
setup.py
anonymization/__init__.py
anonymization/basemodel.py
anonymization/client.py
anonymization/exceptions.py
anonymization/projects.py
anonymization/auth/__init__.py
anonymization/auth/tokens.py
anonymization/auth/users.py
anonymization/infer/__init__.py
anonymization/infer/presign.py
anonymization/infer/folders/__init__.py
anonymization/infer/images/__init__.py
anonymization/infer/images/detections.py
anonymization/infer/videos/__init__.py
anonymization/infer/videos/detections.py
anonymization/infer/videos/frames.py
anonymization/types/__init__.py
anonymization/types/bounding_box.py
anonymization/utils/__init__.py
anonymization/utils/encryption.py
anonymization/utils/videos.py
anonymization_sdk.egg-info/PKG-INFO
anonymization_sdk.egg-info/SOURCES.txt
anonymization_sdk.egg-info/dependency_links.txt
anonymization_sdk.egg-info/requires.txt
anonymization_sdk.egg-info/top_level.txt