Metadata-Version: 2.1
Name: anonymization-sdk
Version: 2.0.4
Summary: The anonymization-sdk provides an API for inferring videos and images.
Author: Streamingo Solutions
Author-email: deeplabel-team@streamingo.ai
Classifier: Development Status :: 5 - Production/Stable
Classifier: Intended Audience :: Developers
Classifier: Topic :: Software Development :: Build Tools
Classifier: License :: OSI Approved :: MIT License
Classifier: Programming Language :: Python :: 3
Classifier: Programming Language :: Python :: 3.6
Classifier: Programming Language :: Python :: 3.7
Classifier: Programming Language :: Python :: 3.8
Classifier: Programming Language :: Python :: 3.9
Classifier: Programming Language :: Python :: 3.10
Classifier: Programming Language :: Python :: 3 :: Only
Requires-Python: >=3.8, <4
Requires-Dist: requests
Requires-Dist: addict
Requires-Dist: pydantic>=1.9
Requires-Dist: case-converter
Requires-Dist: shapely
Requires-Dist: python3-wget
Requires-Dist: pascal-voc-writer
Requires-Dist: opencv-python
Requires-Dist: coloredlogs
Requires-Dist: tqdm
Requires-Dist: dataclasses
Requires-Dist: yarl
Requires-Dist: Pillow
